boston311/__init__.py
boston311/api.py
boston311/constants.py
boston311/datamodels.py
boston311/exceptions.py
boston311/formatting.py
boston311/service_requests_parameters.py
boston311-0.1.1.dist-info/LICENSE
boston311-0.1.1.dist-info/WHEEL
boston311-0.1.1.dist-info/METADATA
boston311-0.1.1.dist-info/RECORD
