Metadata-Version: 2.1
Name: boston311
Version: 0.1.1
Summary: Access service request data from the Boston 311 API.
Author-email: Joshua Cook <joshuacook0023@gmail.com>
Classifier: Intended Audience :: Developers
Classifier: Programming Language :: Python
Classifier: Programming Language :: Python :: 3.9
Classifier: License :: OSI Approved :: GNU General Public License v3 or later (GPLv3+)
Classifier: Operating System :: OS Independent
Classifier: Topic :: Utilities
Classifier: Typing :: Typed
Requires-Dist: requests >=2.25
Requires-Dist: pydantic >=1.8
Requires-Dist: flit >=3.3 ; extra == "dev"
Requires-Dist: keyring >=23.0 ; extra == "dev"
Requires-Dist: tox >=3.24 ; extra == "dev"
Requires-Dist: pdoc3 ; extra == "doc"
Requires-Dist: pytest >=6.2 ; extra == "test"
Requires-Dist: pytest-cov >=2.12 ; extra == "test"
Requires-Dist: pytest-sugar >=0.9 ; extra == "test"
Requires-Dist: tox >=3.24 ; extra == "test"
Requires-Dist: factory-boy >=3.2 ; extra == "test"
Project-URL: Source, https://github.com/jhrcook/boston311
Project-URL: Tracker, https://github.com/jhrcook/boston311/issues
Provides-Extra: dev
Provides-Extra: doc
Provides-Extra: test
